LICENSE
MANIFEST.in
README.rst
setup.py
docs/API.rst
docs/CLI.rst
docs/Development.rst
docs/GUI.rst
docs/Installing.rst
docs/Makefile
docs/MemoryViewer.rst
docs/Payloads.rst
docs/Shell.rst
docs/conf.py
docs/index.rst
pyrasite/__init__.py
pyrasite/injector.py
pyrasite/inspector.py
pyrasite/ipc.py
pyrasite/main.py
pyrasite/reverse.py
pyrasite.egg-info/PKG-INFO
pyrasite.egg-info/SOURCES.txt
pyrasite.egg-info/dependency_links.txt
pyrasite.egg-info/entry_points.txt
pyrasite.egg-info/not-zip-safe
pyrasite.egg-info/top_level.txt
pyrasite/payloads/__init__.py
pyrasite/payloads/dump_memory.py
pyrasite/payloads/dump_modules.py
pyrasite/payloads/dump_stacks.py
pyrasite/payloads/force_garbage_collection.py
pyrasite/payloads/helloworld.py
pyrasite/payloads/reverse_python_shell.py
pyrasite/payloads/reverse_shell.py
pyrasite/payloads/start_callgraph.py
pyrasite/payloads/stop_callgraph.py
pyrasite/tests/__init__.py
pyrasite/tests/context_manager_case.py
pyrasite/tests/test_code_injection.py
pyrasite/tests/test_ipc.py
pyrasite/tests/utils.py
pyrasite/tools/__init__.py
pyrasite/tools/memory_viewer.py
pyrasite/tools/shell.py