Metadata-Version: 1.1
Name: pyrasite
Version: 2.0
Summary: Inject code into a running Python process
Home-page: http://pyrasite.com
Author: Luke Macken
Author-email: lmacken@redhat.com
License: GPLv3
Keywords: debugging injection runtime
Platform: UNKNOWN
Classifier: Development Status :: 4 - Beta
Classifier: Environment :: Console
Classifier: Intended Audience :: Developers
Classifier: Intended Audience :: System Administrators
Classifier: License :: OSI Approved :: GNU General Public License (GPL)
Classifier: Topic :: System :: Monitoring
Classifier: Topic :: Software Development :: Debuggers
Classifier: Programming Language :: Python
Classifier: Programming Language :: Python :: 3
